[
    {
        "Holder": "Blackrock Inc.",
        "Shares": "15.9M",
        "Date Reported": "Sep 30, 2024",
        "% Out": "12.38%",
        "Value": "142,123,518"
    },
    {
        "Holder": "Vanguard Group Inc",
        "Shares": "13.58M",
        "Date Reported": "Sep 30, 2024",
        "% Out": "10.58%",
        "Value": "121,403,889"
    },
    {
        "Holder": "Baupost Group, Inc,.(The) LLC",
        "Shares": "12.22M",
        "Date Reported": "Sep 30, 2024",
        "% Out": "9.52%",
        "Value": "109,269,949"
    },
    {
        "Holder": "Ontario Teachers' Pension Plan Board",
        "Shares": "8.55M",
        "Date Reported": "Sep 30, 2024",
        "% Out": "6.66%",
        "Value": "76,395,282"
    },
    {
        "Holder": "Canada Pension Plan Investment Board",
        "Shares": "8.55M",
        "Date Reported": "Sep 30, 2024",
        "% Out": "6.66%",
        "Value": "76,395,282"
    },
    {
        "Holder": "Warburg Pincus LLC",
        "Shares": "8.39M",
        "Date Reported": "Sep 30, 2024",
        "% Out": "6.54%",
        "Value": "75,012,738"
    },
    {
        "Holder": "State Street Corporation",
        "Shares": "4.45M",
        "Date Reported": "Sep 30, 2024",
        "% Out": "3.46%",
        "Value": "39,745,548"
    },
    {
        "Holder": "Disciplined Growth Investors, Inc.",
        "Shares": "4.42M",
        "Date Reported": "Sep 30, 2024",
        "% Out": "3.44%",
        "Value": "39,507,851"
    },
    {
        "Holder": "Neuberger Berman Group, LLC",
        "Shares": "4.34M",
        "Date Reported": "Sep 30, 2024",
        "% Out": "3.38%",
        "Value": "38,833,847"
    },
    {
        "Holder": "Geode Capital Management, LLC",
        "Shares": "2.51M",
        "Date Reported": "Sep 30, 2024",
        "% Out": "1.95%",
        "Value": "22,422,019"
    }
]