[
    {
        "Holder": "Vanguard Group Inc",
        "Shares": "148.77M",
        "Date Reported": "Sep 30, 2024",
        "% Out": "9.17%",
        "Value": "18,631,769,878"
    },
    {
        "Holder": "Blackrock Inc.",
        "Shares": "129.52M",
        "Date Reported": "Sep 30, 2024",
        "% Out": "7.98%",
        "Value": "16,220,562,147"
    },
    {
        "Holder": "State Street Corporation",
        "Shares": "70.17M",
        "Date Reported": "Sep 30, 2024",
        "% Out": "4.32%",
        "Value": "8,788,124,590"
    },
    {
        "Holder": "JP Morgan Chase & Company",
        "Shares": "40.16M",
        "Date Reported": "Jun 30, 2024",
        "% Out": "2.47%",
        "Value": "5,030,154,428"
    },
    {
        "Holder": "Price (T.Rowe) Associates Inc",
        "Shares": "35.31M",
        "Date Reported": "Sep 30, 2024",
        "% Out": "2.18%",
        "Value": "4,421,996,387"
    },
    {
        "Holder": "Geode Capital Management, LLC",
        "Shares": "34.24M",
        "Date Reported": "Sep 30, 2024",
        "% Out": "2.11%",
        "Value": "4,288,698,824"
    },
    {
        "Holder": "Morgan Stanley",
        "Shares": "30.4M",
        "Date Reported": "Sep 30, 2024",
        "% Out": "1.87%",
        "Value": "3,806,810,504"
    },
    {
        "Holder": "FMR, LLC",
        "Shares": "26.7M",
        "Date Reported": "Sep 30, 2024",
        "% Out": "1.65%",
        "Value": "3,344,521,994"
    },
    {
        "Holder": "Fisher Asset Management, LLC",
        "Shares": "23.8M",
        "Date Reported": "Sep 30, 2024",
        "% Out": "1.47%",
        "Value": "2,980,115,305"
    },
    {
        "Holder": "Norges Bank Investment Management",
        "Shares": "22.46M",
        "Date Reported": "Jun 30, 2024",
        "% Out": "1.38%",
        "Value": "2,812,950,216"
    }
]